{"id":"248","title":"Indented Horizontal Menu","structure":"basic","depth":"1","active":"1","terms":["horizontal","pure-css"],"thumbnail":"248\/thumbnail\/css_menu_thumb.png","images":[],"css":"@charset \"UTF-8\";\r\n@import url(http:\/\/fonts.googleapis.com\/css?family=Lato:300,400,700);\r\n\r\n@main_color :  [[main_color:#2a8a8f]];\r\n@menu_width : [[menu_width:auto]];\r\n@menu_align : left;\r\n@menu_font_size : [[menu_font_size: 16px]];\r\n@menu_text_color : [[menu_text_color:#fff]];\r\n\r\n\r\n\/\/ Less Styles\r\n@light-color: lighten(@main_color, 10%);\r\n@light-color1: lighten(@main_color, 20%);\r\n@light-color2: lighten(@main_color, 20%);\r\n@dark-color: darken(@main_color, 10%);\r\n@dark-color1: darken(@main_color, 20%);\r\n@dark-color2: darken(@main_color, 30%);\r\n@dark-color3: darken(@main_color, 40%);\r\n\r\n.rounded-corners (@radius: 5px) {\r\n  -webkit-border-radius: @radius;\r\n  -moz-border-radius: @radius;\r\n  -ms-border-radius: @radius;\r\n  -o-border-radius: @radius;\r\n  border-radius: @radius;\r\n}\r\n\r\n.rounded-corner (@1, @2, @3, @4) {\r\n  -webkit-border-radius: @1 @2 @3 @4;\r\n  -moz-border-radius: @1 @2 @3 @4;\r\n  -ms-border-radius: @1 @2 @3 @4;\r\n  -o-border-radius: @1 @2 @3 @4;\r\n  border-radius: @1 @2 @3 @4;\r\n}\r\n\r\n.linear-gradient (@top-color, @bottom-color) {\r\n\tbackground: @top-color; \r\n\tbackground:-moz-linear-gradient(top, @top-color 0%, @bottom-color 100%); \r\n\tbackground:-webkit-gradient(linear, left top, left bottom, color-stop(0%,@top-color), color-stop(100%,@bottom-color)); \r\n\tbackground:-webkit-linear-gradient(top, @top-color 0%,@bottom-color 100%); \r\n\tbackground:-o-linear-gradient(top, @top-color 0%,@bottom-color 100%); \r\n\tbackground:-ms-linear-gradient(top, @top-color 0%,@bottom-color 100%); \r\n\tbackground:linear-gradient(top, @top-color 0%,@bottom-color 100%); \r\n\tfilter:progid:DXImageTransform.Microsoft.gradient( startColorstr='@top-color', endColorstr='@bottom-color',GradientType=0 ); \r\n}\r\n\r\n.box-shadow(@x, @y, @spread, @color) {\r\n\t-moz-box-shadow: @x @y @spread @color;\r\n\t-webkit-box-shadow:@x @y @spread @color;\r\n\tbox-shadow: @x @y @spread @color;\r\n}\r\n\r\n.box-shadow-inset(@x, @y, @spread, @color) {\r\n\t-moz-box-shadow: inset @x @y @spread @color;\r\n\t-webkit-box-shadow: inset @x @y @spread @color;\r\n\tbox-shadow: inset @x @y @spread @color;\r\n}\r\n.text-shadow(@x, @y, @spread, @color) {\r\n\t-webkit-text-shadow: @x @y @spread @color;\r\n\t-moz-text-shadow: @x @y @spread @color;\r\n\r\n}\r\n.clearfix() {\r\n  zoom: 1;\r\n  &:before { content: ''; display: block; }\r\n  &:after { content: ''; display: table; clear: both; }\r\n}\r\n\r\n\r\n\/* Base Styles *\/\r\n#cssmenu ul, \r\n#cssmenu li,\r\n#cssmenu a {\r\n list-style: none;\r\n margin: 0;\r\n padding: 0;\r\n border: 0;\r\n line-height: 1;\r\n font-family: 'Lato', sans-serif;\r\n}\r\n\r\n#cssmenu {\r\n\tborder: 1px solid @dark-color1;\r\n\t.rounded-corners(5px);\r\n        width: @menu_width;\r\n}\r\n#cssmenu ul {\r\n .clearfix;\t\r\n .linear-gradient (@light-color, @main_color);\r\n padding: 5px 10px;\r\n\t.rounded-corners(5px);\r\n}\r\n#cssmenu li {\r\n\tfloat: left;\r\n\tmargin: 0 5px 0 0;\r\n\tborder: 1px solid transparent;\t\r\n}\r\n#cssmenu li a {\r\n  .rounded-corners(5px);\r\n\tpadding: 8px 15px 9px 15px;\r\n\tdisplay: block;\r\n\ttext-decoration: none;\r\n\tcolor: @menu_text_color;\r\n\tborder: 1px solid transparent;\r\n    font-size: @menu_font_size;\r\n}\r\n\r\n#cssmenu li.active {\r\n  .rounded-corners(5px);\r\n\tborder: 1px solid @light-color;\r\n}\r\n\r\n#cssmenu li.active a {\r\n  .rounded-corners(5px);\r\n\tdisplay: block;\r\n\tbackground: @dark-color;\r\n\tborder: 1px solid @dark-color1;\r\n\t.box-shadow-inset(0, 5px, 10px, @dark-color1);\r\n}\r\n\r\n#cssmenu li:hover {\r\n  .rounded-corners(5px);\r\n\tborder: 1px solid @light-color;\r\n}\r\n\r\n#cssmenu li:hover a {\r\n  .rounded-corners(5px);\r\n\tdisplay: block;\r\n\tbackground: @dark-color;\r\n\tborder: 1px solid @dark-color1;\r\n\t.box-shadow-inset(0, 5px, 10px, @dark-color1);\r\n}\r\n","jquery":""}