{"id":"205","title":"Platinum Flyout Menu","structure":"basic","depth":"3","active":"0","terms":["vertical","flyout","css3"],"thumbnail":"205\/thumbnail\/css_menu_thumb.png","images":[],"css":"\/* Starter CSS for Flyout Menu *\/\n#menu_class# {\n  padding: 0;\n  margin: 0;\n  border: 0; }\n\n#menu_class# ul, li {\n  list-style: none;\n  margin: 0;\n  padding: 0; }\n\n#menu_class# ul {\n  position: relative;\n  z-index: 597;\n  float: left; }\n\n#menu_class# ul li {\n  float: left;\n  min-height: 1px;\n  line-height: 1em;\n  vertical-align: middle; }\n\n#menu_class# ul li.hover,\n#menu_class# ul li:hover {\n  position: relative;\n  z-index: 599;\n  cursor: default; }\n\n#menu_class# ul ul {\n  visibility: hidden;\n  position: absolute;\n  top: 100%;\n  left: 0;\n  z-index: 598;\n  width: 100%; }\n\n#menu_class# ul ul li {\n  float: none; }\n\n#menu_class# ul li:hover > ul {\n  visibility: visible; }\n\n#menu_class# ul ul {\n  top: 0;\n  left: 100%; }\n\n#menu_class# ul li {\n  float: none; }\n\n\/* Custom Stuff *\/\n#menu_class# {\n  -moz-border-radius: 5px;\n  -webkit-border-radius: 5px;\n  border-radius: 5px;\n  -moz-background-clip: padding;\n  -webkit-background-clip: padding-box;\n  background-clip: padding-box;\n  -moz-box-shadow: 0 0 2px 1px rgba(0, 0, 0, 0.15);\n  -webkit-box-shadow: 0 0 2px 1px rgba(0, 0, 0, 0.15);\n  box-shadow: 0 0 2px 1px rgba(0, 0, 0, 0.15);\n  width: [[menu_width:200px]]; \n}\n  #menu_class# span, #menu_class# a {\n    display: inline-block;\n    font-family: Arial, Helvetica, sans-serif;\n    font-size: 12px;\n    text-decoration: none; }\n  #menu_class#:after, #menu_class# ul:after {\n    content: '';\n    display: block;\n    clear: both; }\n  #menu_class# > ul > li:first-child {\n    -moz-border-radius: 5px 5px 0 0;\n    -webkit-border-radius: 5px 5px 0 0;\n    border-radius: 5px 5px 0 0;\n    -moz-background-clip: padding;\n    -webkit-background-clip: padding-box;\n    background-clip: padding-box; }\n  #menu_class# > ul > li:last-child {\n    -moz-border-radius: 0 0 5px 5px;\n    -webkit-border-radius: 0 0 5px 5px;\n    border-radius: 0 0 5px 5px;\n    -moz-background-clip: padding;\n    -webkit-background-clip: padding-box;\n    background-clip: padding-box; }\n  #menu_class# > ul > li ul ul {\n    -moz-border-radius: 0 6px 6px 0;\n    -webkit-border-radius: 0 6px 6px 0;\n    border-radius: 0 6px 6px 0;\n    -moz-background-clip: padding;\n    -webkit-background-clip: padding-box;\n    background-clip: padding-box; }\n  #menu_class# > ul > li ul ul li:first-child {\n    -moz-border-radius: 0 5px 0 0;\n    -webkit-border-radius: 0 5px 0 0;\n    border-radius: 0 5px 0 0;\n    -moz-background-clip: padding;\n    -webkit-background-clip: padding-box;\n    background-clip: padding-box; }\n  #menu_class# > ul > li ul ul li:last-child {\n    -moz-border-radius: 0 0 5px 0;\n    -webkit-border-radius: 0 0 5px 0;\n    border-radius: 0 0 5px 0;\n    -moz-background-clip: padding;\n    -webkit-background-clip: padding-box;\n    background-clip: padding-box; }\n  #menu_class# ul, #menu_class# li {\n    width: 100%; }\n  #menu_class# li {\n    background: #dddddd url(data:image\/png;base64,iVBORw0KGgoAAAANSUhEUgAAAAoAAAAJCAMAAAA8eE0hAAAAUVBMVEX\/\/\/\/MzMzMzMzMzMzMzMzMzMzMzMzMzMzMzMzMzMzMzMzNzc3l5eXg4ODZ2dnMzMzi4uLS0tLe3t7Q0NDV1dXj4+PW1tbk5OTc3NzPz8\/R0dH0Zv5RAAAAC3RSTlMAM2YekAmlPHuEAwArv7wAAAA\/SURBVHheY2Dl5mdigABGKV5BNnYok4dHQpKFGcrkEefj5gAzQUBABM7kFYQyRcX4mUBMkEpOLrA2IWGwfgYAn0UDZszv8IwAAAAASUVORK5CYII=) repeat-x;\n    background-image: -webkit-gradient(linear, left top, left bottom, color-stop(0, #e5e5e5), color-stop(1, #dddddd));\n    background-image: -webkit-linear-gradient(top, #e5e5e5, #dddddd);\n    background-image: -moz-linear-gradient(top, #e5e5e5, #dddddd);\n    background-image: -ms-linear-gradient(top, #e5e5e5, #dddddd);\n    background-image: -o-linear-gradient(top, #e5e5e5, #dddddd);\n    background-image: linear-gradient(#e5e5e5, #dddddd); }\n    #menu_class# li:hover {\n      background: #f6f6f6; }\n  #menu_class# a {\n    color: #666666;\n    line-height: 160%;\n    padding: 11px 28px 11px 28px;\n    width: 144px; }\n  #menu_class# ul ul {\n    width: [[sub_menu_width: 200px]];\n    border: 1px solid #dddddd;\n    -moz-box-shadow: 0 1px 2px rgba(0, 0, 0, 0.15);\n    -webkit-box-shadow: 0 1px 2px rgba(0, 0, 0, 0.15);\n    box-shadow: 0 1px 2px rgba(0, 0, 0, 0.15); }\n    #menu_class# ul ul li {\n      background: #f6f6f6; }\n      #menu_class# ul ul li:hover {\n        background: #dddddd; }\n        #menu_class# ul ul li:hover a {\n          color: [[menu_background_color:#AE0001]]; }\n      #menu_class# ul ul li ul li {\n        background: #dddddd; }\n        #menu_class# ul ul li ul li:hover {\n          background: #b7b7b7; }\n  #menu_class# .has-sub {\n    position: relative; }\n    #menu_class# .has-sub:after, #menu_class# .has-sub > ul > .has-sub:hover:after {\n      content: '';\n      display: block;\n      width: 10px;\n      height: 9px;\n      position: absolute;\n      right: 5px;\n      top: 50%;\n      margin-top: -5px;\n      background-image: url(data:image\/png;base64,iVBORw0KGgoAAAANSUhEUgAAAAoAAAAJCAMAAAA8eE0hAAAAUVBMVEX\/\/\/\/MzMzMzMzMzMzMzMzMzMzMzMzMzMzMzMzMzMzMzMzNzc3l5eXg4ODZ2dnMzMzi4uLS0tLe3t7Q0NDV1dXj4+PW1tbk5OTc3NzPz8\/R0dH0Zv5RAAAAC3RSTlMAM2YekAmlPHuEAwArv7wAAAA\/SURBVHheY2Dl5mdigABGKV5BNnYok4dHQpKFGcrkEefj5gAzQUBABM7kFYQyRcX4mUBMkEpOLrA2IWGwfgYAn0UDZszv8IwAAAAASUVORK5CYII=);\n      -moz-transform: rotate(360deg);\n      -o-transform: rotate(360deg);\n      -ms-transform: rotate(360deg);\n      -webkit-transform: rotate(360deg);\n      transform: rotate(360deg); }\n    #menu_class# .has-sub > ul > .has-sub:after, #menu_class# .has-sub:hover:after {\n      background-image: url(data:image\/png;base64,iVBORw0KGgoAAAANSUhEUgAAAAoAAAAJCAMAAAA8eE0hAAAAUVBMVEX\/\/\/\/d3d3d3d3d3d3d3d3d3d3d3d3d3d3d3d3d3d3d3d3e3t729vbx8fHq6urd3d3z8\/Pj4+Pv7+\/h4eHm5ub09PTn5+f19fXt7e3g4ODi4uLUsVdlAAAAC3RSTlMAM2YekAmlPHuEAwArv7wAAAA\/SURBVHheY2Dl5mdigABGKV5BNnYok4dHQpKFGcrkEefj5gAzQUBABM7kFYQyRcX4mUBMkEpOLrA2IWGwfgYAn0UDZszv8IwAAAAASUVORK5CYII=); }\n","jquery":""}